pipedocs/__init__.py
pipedocs/__main__.py
pipedocs/cmdline.py
pipedocs/exceptions.py
pipedocs/commands/__init__.py
pipedocs/commands/rundocumenter.py
pipedocs/commands/rungenerator.py
pipedocs/documenters/__init__.py
pipedocs/exporters/__init__.py
pipedocs/exporters/folder.py
pipedocs/exporters/markdown.py
pipedocs/generators/__init__.py
pipedocs/importers/__init__.py
pipedocs/importers/base.py
pipedocs/importers/local.py
pipedocs/models/__init__.py
pipedocs/settings/__init__.py
pipedocs/settings/default_settings.py
pipedocs/utils/__init__.py
pipedocs/utils/conf.py
pipedocs/utils/misc.py
pipedocs/utils/project.py
pipedocs/utils/python.py
pipedocs-0.1.2.dist-info/LICENSE
pipedocs-0.1.2.dist-info/METADATA
pipedocs-0.1.2.dist-info/WHEEL
pipedocs-0.1.2.dist-info/top_level.txt
pipedocs-0.1.2.dist-info/RECORD
