Metadata-Version: 2.1
Name: pipedocs
Version: 0.1.2
Summary: CLI tool to automatically generate documentatino for Azure Data Factory Pipelines and Azure Synapse Pipelines
Author-email: Leonardo Benitez <lsbenitezpereira@gmail.com>
License: MIT License
Project-URL: repository, https://github.com/skaylink/pipedocs
Project-URL: documentation, https://github.com/skaylink/pipedocs
Keywords: automatic documentation,azure
Classifier: License :: OSI Approved :: MIT License
Classifier: Programming Language :: Python
Classifier: Programming Language :: Python :: 3
Classifier: Environment :: Console
Classifier: Topic :: Software Development :: Libraries :: Python Modules
Requires-Python: >=3.7
License-File: LICENSE
Requires-Dist: pydantic >=2.1.0
Provides-Extra: build
Requires-Dist: build ; extra == 'build'
Requires-Dist: twine ; extra == 'build'
Provides-Extra: dev
Requires-Dist: python-dotenv ; extra == 'dev'
